mysoccer_update/__init__.py
mysoccer_update/api_client.py
mysoccer_update/config.py
mysoccer_update/fixtures.py
mysoccer_update/guncelle.py
mysoccer_update/results.py
puan_durumu_modular/__init__.py
puan_durumu_modular/main.py
puan_durumu_modular/calculators/__init__.py
puan_durumu_modular/calculators/base_calculator.py
puan_durumu_modular/calculators/standings_calculator.py
puan_durumu_modular/calculators/stats_calculator.py
puan_durumu_modular/core/__init__.py
puan_durumu_modular/core/database.py
puan_durumu_modular/core/match_loader.py
puan_durumu_modular/core/week_divider.py
puan_durumu_modular/exporters/__init__.py
puan_durumu_modular/exporters/excel_exporter.py
puan_durumu_modular/services/__init__.py
puan_durumu_modular/services/week_divider_service.py
puan_durumu_modular/utils/__init__.py
puan_durumu_modular/utils/helpers.py
mysoccer_update-1.0.1.dist-info/METADATA
mysoccer_update-1.0.1.dist-info/WHEEL
mysoccer_update-1.0.1.dist-info/top_level.txt
mysoccer_update-1.0.1.dist-info/RECORD
