Metadata-Version: 2.4
Name: mysoccer-update
Version: 1.0.1
Summary: Mackolik.com API'den futbol maç verilerini çeken modüler Python kütüphanesi
Home-page: https://github.com/ahmety/mysoccer-update
Author: ahmety
Author-email: your-email@example.com
Project-URL: Bug Tracker, https://github.com/ahmety/mysoccer-update/issues
Project-URL: Documentation, https://github.com/ahmety/mysoccer-update#readme
Project-URL: Source Code, https://github.com/ahmety/mysoccer-update
Keywords: football soccer data scraping mackolik api mysoccer
Classifier: Development Status :: 4 - Beta
Classifier: Intended Audience :: Developers
Classifier: License :: OSI Approved :: MIT License
Classifier: Programming Language :: Python :: 3
Classifier: Programming Language :: Python :: 3.9
Classifier: Programming Language :: Python :: 3.10
Classifier: Programming Language :: Python :: 3.11
Classifier: Programming Language :: Python :: 3.12
Classifier: Topic :: Internet :: WWW/HTTP :: Dynamic Content
Classifier: Topic :: Software Development :: Libraries :: Python Modules
Requires-Python: >=3.9
Requires-Dist: requests>=2.31.0
Requires-Dist: pandas>=2.0.0
Requires-Dist: psycopg>=3.1.0
Requires-Dist: openpyxl>=3.1.0
Provides-Extra: dev
Requires-Dist: pytest>=7.0.0; extra == "dev"
Requires-Dist: black>=23.0.0; extra == "dev"
Requires-Dist: flake8>=6.0.0; extra == "dev"
Provides-Extra: scheduler
Requires-Dist: schedule>=1.2.0; extra == "scheduler"
Dynamic: author
Dynamic: author-email
Dynamic: classifier
Dynamic: description
Dynamic: description-content-type
Dynamic: home-page
Dynamic: keywords
Dynamic: project-url
Dynamic: provides-extra
Dynamic: requires-dist
Dynamic: requires-python
Dynamic: summary
